{
  "timestamp": "2025-11-16T11:52:28.418401634+08:00",
  "cycle_number": 146,
  "system_prompt": "",
  "input_prompt": "",
  "cot_trace": "让我先分析当前市场状况和持仓情况：\n\n**宏观分析：**\n- BTC：1小时EMA(20)=95771 \u003c EMA(50)=96734，MACD为负，RSI=47.78 \u003c 50 → BEARISH_MACRO\n- ETH：1小时EMA(20)=3177 \u003c EMA(50)=3207，MACD为负，RSI=54.42 \u003e 50但接近中性 → BEARISH_MACRO\n- SOL：1小时EMA(20)=140.79 \u003c EMA(50)=142.75，MACD为负，RSI=50.63 \u003e 50但接近中性 → BEARISH_MACRO\n\n整体市场处于看跌宏观结构，适合寻找做空机会。\n\n**当前持仓分析：**\n1. SOLUSDT空头：入场141.24，当前141.23，盈亏+0.01%\n   - 15分钟RSI(7)=70.20 \u003e 70（超买），MACD为正但很小\n   - 价格在EMA20上方，但1小时趋势看跌\n   - 建议持有，等待回调\n\n2. ETHUSDT空头：入场3195.64，当前3199.33，盈亏-0.12%\n   - 15分钟RSI(7)=71.24 \u003e 70（超买），MACD为正\n   - 价格在EMA20上方，但1小时趋势看跌\n   - 建议持有，等待回调\n\n**候选币种分析：**\n\n1. BTCUSDT：看跌宏观，15分钟RSI(7)=58.80，MACD为正但很小，没有明显入场信号\n\n2. ETHUSDT：已有持仓，不建议加仓\n\n3. SOLUSDT：已有持仓，不建议加仓\n\n4. BNBUSDT：1小时EMA20=934.52 ≈ EMA50=934.54（中性），但15分钟RSI(7)=71.42 \u003e 70（超买），MACD为正，当前价格941.54 \u003e EMA20=935.17，有做空机会\n\n5. HYPEUSDT：1小时EMA20=38.60 \u003e EMA50=38.47（看涨），15分钟RSI(7)=52.55（中性），MACD接近0，没有明显信号\n\n**BNBUSDT做空机会分析：**\n- 宏观：中性偏弱（EMA20≈EMA50）\n- 15分钟：RSI(7)=71.42 \u003e 70（超买），MACD为正但可能见顶\n- 形态：价格创新高后RSI背离，可能形成High2做空形态\n- 风险计算：ATR(3)=8.172，止损=当前价+8.17=949.71，止盈=934.17（前期支撑），风险比≈1:2.5\n\n**风险检查：**\n- 当前持仓2个，可开新仓\n- 保证金使用率74.2%，有空间\n- 账户净值95.44，单笔风险应≤1.91 USDT\n- BNB仓位计算：风险8.17点，仓位=1.91/8.17=0.234 BNB ≈ 220 USDT（符合要求）",
  "decision_json": "[\n  {\n    \"symbol\": \"SOLUSDT\",\n    \"action\": \"hold\",\n    \"reasoning\": \"空头持仓中,15分钟RSI超买但1小时趋势看跌,等待回调\"\n  },\n  {\n    \"symbol\": \"ETHUSDT\",\n    \"action\": \"hold\",\n    \"reasoning\": \"空头持仓中,15分钟RSI超买但1小时趋势看跌,等待回调\"\n  },\n  {\n    \"symbol\": \"BNBUSDT\",\n    \"action\": \"open_short\",\n    \"leverage\": 3,\n    \"position_size_usd\": 220,\n    \"stop_loss\": 949.71,\n    \"take_profit\": 934.17,\n    \"confidence\": 75,\n    \"risk_usd\": 1.91,\n    \"reasoning\": \"中性宏观中RSI超买背离,形成High2做空形态,风险比1:2.5\"\n  }\n]",
  "account_state": {
    "total_balance": 95.44163107,
    "available_balance": 25.03750636,
    "total_unrealized_profit": -4.55836893,
    "position_count": 2,
    "margin_used_pct": 74.23394299290239
  },
  "positions": [
    {
      "symbol": "SOLUSDT",
      "side": "short",
      "position_amt": 0.54,
      "entry_price": 141.24,
      "mark_price": 141.22,
      "unrealized_profit": 0.0108,
      "leverage": 3,
      "liquidation_price": 187.32183882
    },
    {
      "symbol": "ETHUSDT",
      "side": "short",
      "position_amt": 0.071,
      "entry_price": 3195.64,
      "mark_price": 3199.33,
      "unrealized_profit": -0.26199,
      "leverage": 5,
      "liquidation_price": 3817.90854582
    }
  ],
  "candidate_coins": [
    "BTCUSDT",
    "ETHUSDT",
    "SOLUSDT",
    "BNBUSDT",
    "HYPEUSDT"
  ],
  "decisions": null,
  "execution_log": [],
  "success": false,
  "error_message": "获取AI决策失败: 解析AI响应失败: 决策验证失败: 决策 #3 验证失败: 山寨币单币种仓位价值不能超过143 USDT（1.5倍账户净值），实际: 220"
}